LICENSE.txt
distribute_setup.py
setup.cfg
setup.py
doc/Makefile
doc/make.bat
doc/source/conf.py
doc/source/index.rst
doc/source/interp2d.rst
src/bilinearinterp.c
stsci/__init__.py
stsci.imagemanip.egg-info/PKG-INFO
stsci.imagemanip.egg-info/SOURCES.txt
stsci.imagemanip.egg-info/dependency_links.txt
stsci.imagemanip.egg-info/namespace_packages.txt
stsci.imagemanip.egg-info/not-zip-safe
stsci.imagemanip.egg-info/requires.txt
stsci.imagemanip.egg-info/top_level.txt
stsci/imagemanip/__init__.py
stsci/imagemanip/interp2d.py
stsci/imagemanip/version.py
stsci/imagemanip/tests/__init__.py
stsci/imagemanip/tests/testImageManip.py